isegcan-0.6.1.dist-info/licenses/LICENCE
src/_edcp_definitions.py
src/can_edcp.py
venv/bin/activate_this.py
isegcan-0.6.1.dist-info/METADATA
isegcan-0.6.1.dist-info/WHEEL
isegcan-0.6.1.dist-info/top_level.txt
isegcan-0.6.1.dist-info/RECORD
