Metadata-Version: 2.4
Name: isegcan
Version: 0.6.1
Summary: Simple library to control older ISEG HV supplies over CAN interface.
Author-email: Timo Hildén <timo.hilden@helsinki.fi>
License-Expression: MIT
Project-URL: Homepage, https://codeberg.org/stgermain77/isegcan
Project-URL: Issues, https://codeberg.org/stgermain77/isegcan/issues
Classifier: Programming Language :: Python :: 3
Classifier: Operating System :: POSIX :: Linux
Classifier: Development Status :: 4 - Beta
Requires-Python: >=3.9
License-File: LICENCE
Requires-Dist: python-can
Dynamic: license-file
